Workbook
Name SegmentaciónDeDatos_Categoría: #N/A
Name SegmentaciónDeDatos_Región: #N/A

Sheet KPI Dashboard
B2: TECHPERU S.A.C. - KPI DASHBOARD 2025
B3: Total Ingreso Neto | C3: =SUM(Ventas!K3:K281) -> 1793322 | D3: Total Ganancia | F3: =SUM(Ventas!M3:M281) -> 628069.73 | J3: Mejor Vendedor
B5: Nro. De Ventas | C5: =COUNTA(Ventas!A3:A281) -> 279 | D5: Promedio Por Ventas | F5: =AVERAGE(Ventas!K3:K281) -> 6427.6774 | J5: Ana Torres | K5: =SUMIF(Ventas!C:C,J5,Ventas!K:K) -> 360906
B7: Mejor Vendedor | C7: =INDEX(J5:J11,MATCH(MAX(K5:K11),K5:K11,0)) -> Miguel Paz | D7: Categoria TOP | F7: =INDEX(J14:J18,MATCH(MAX(K14:K18),K14:K18,0)) -> Laptops | J7: Carlos Ríos | K7: =SUMIF(Ventas!C:C,J7,Ventas!K:K) -> 304999.5
J8: Diego Mora | K8: =SUMIF(Ventas!C:C,J8,Ventas!K:K) -> 270691.75
J9: Lucía Vega | K9: =SUMIF(Ventas!C:C,J9,Ventas!K:K) -> 302819.5
J10: Miguel Paz | K10: =SUMIF(Ventas!C:C,J10,Ventas!K:K) -> 366852.25
J11: Sofía Luna | K11: =SUMIF(Ventas!C:C,J11,Ventas!K:K) -> 187053
J14: Laptops | K14: =SUMIF(Ventas!E:E,J14,Ventas!K:K) -> 909400
J15: Monitores | K15: =SUMIF(Ventas!E:E,J15,Ventas!K:K) -> 397792.5
J16: Redes | K16: =SUMIF(Ventas!E:E,J16,Ventas!K:K) -> 82777.5
J17: Periféricos | K17: =SUMIF(Ventas!E:E,J17,Ventas!K:K) -> 67833.5
J18: Software | K18: =SUMIF(Ventas!E:E,J18,Ventas!K:K) -> 335518.5

Sheet Análisis
B2: CONSULTA DINÁNICA
B4: Vendedor: | C4: Ana Torres
B5: Categoría: | C5: Monitores
B6: Región: | C6: Lima Sur
B8: Resultados:
B9: Total Ventas (Vendedor + Categoría): | C9: =SUMIFS(Ventas!K3:K281, Ventas!C3:C281, C4, Ventas!E3:E281, C5) -> 85505.5
B10: Total Ventas (Vendedor + Región): | C10: =SUMIFS(Ventas!K3:K281, Ventas!C3:C281, C4, Ventas!D3:D281, C6) -> 61750.5
B11: Nro. de Ventas (Vendedor + Categoría): | C11: =COUNTIFS(Ventas!C3:C281, C4, Ventas!E3:E281, C5) -> 13
B12: Promedio de Venta (Vendedor): | C12: =AVERAGEIF(Ventas!C3:C281, C4, Ventas!K3:K281) -> 7365.4286
B13: Mejor Venta del Vendedor: | C13: =_xlfn.MAXIFS(Ventas!K3:K281, Ventas!C3:C281, C4) -> 37500
B14: Peor Venta del Vendedor: | C14: =_xlfn.MINIFS(Ventas!K3:K281, Ventas!C3:C281, C4) -> 95
B16: BÚSQUEDA POR ID
B17: ID de Venta: | C17: V-0048
B18: Vendedor: | C18: =_xlfn.XLOOKUP(C17, Ventas!A3:A281, Ventas!C3:C281, "No encontrado") -> Ana Torres
B19: Producto: | C19: =_xlfn.XLOOKUP(C17, Ventas!A3:A281, Ventas!F3:F281, "No encontrado") -> Teclado Logitech
B20: Región: | C20: =_xlfn.XLOOKUP(C17, Ventas!A3:A281, Ventas!D3:D281, "No encontrado") -> Provincias
B21: Ingreso Neto: | C21: =_xlfn.XLOOKUP(C17, Ventas!A3:A281, Ventas!K3:K281, "No encontrado") -> 1080
B22: Estado Meta: | C22: =_xlfn.XLOOKUP(C17, Ventas!A3:A281, Ventas!N3:N281, "No encontrado") -> Meta No Alcanzada

Sheet Reporte Mensual
B2: REPORTE MENSUAL DE VENTAS 2024
B4: Mes: | C4: Ingreso Neto: | D4: Nro. Ventas: | E4: Promedio:
B5: Enero | C5: {=SUMPRODUCT((MONTH(Ventas!B3:B281)=1)*Ventas!K3:K281)} -> 192480.25 | D5: {=SUMPRODUCT((MONTH(Ventas!B3:B281)=1)*1)} -> 28 | E5: =AVERAGE(C5,D5) -> 96254.125
B6: Febrero | C6: {=SUMPRODUCT((MONTH(Ventas!B3:B281)=2)*Ventas!K3:K281)} -> 134405.5 | D6: {=SUMPRODUCT((MONTH(Ventas!B3:B281)=2)*1)} -> 18 | E6: =AVERAGE(C6,D6) -> 67211.75
B7: Marzo | C7: {=SUMPRODUCT((MONTH(Ventas!B3:B281)=3)*Ventas!K3:K281)} -> 235123.5 | D7: {=SUMPRODUCT((MONTH(Ventas!B3:B281)=3)*1)} -> 28 | E7: =AVERAGE(C7,D7) -> 117575.75
B8: Abril | C8: {=SUMPRODUCT((MONTH(Ventas!B3:B281)=4)*Ventas!K3:K281)} -> 190678 | D8: {=SUMPRODUCT((MONTH(Ventas!B3:B281)=4)*1)} -> 27 | E8: =AVERAGE(C8,D8) -> 95352.5
B9: Mayo | C9: {=SUMPRODUCT((MONTH(Ventas!B3:B281)=5)*Ventas!K3:K281)} -> 108673.5 | D9: {=SUMPRODUCT((MONTH(Ventas!B3:B281)=5)*1)} -> 26 | E9: =AVERAGE(C9,D9) -> 54349.75
B10: Junio | C10: {=SUMPRODUCT((MONTH(Ventas!B3:B281)=6)*Ventas!K3:K281)} -> 124635 | D10: {=SUMPRODUCT((MONTH(Ventas!B3:B281)=6)*1)} -> 24 | E10: =AVERAGE(C10,D10) -> 62329.5
B11: Julio | C11: {=SUMPRODUCT((MONTH(Ventas!B3:B281)=7)*Ventas!K3:K281)} -> 161476.25 | D11: {=SUMPRODUCT((MONTH(Ventas!B3:B281)=7)*1)} -> 21 | E11: =AVERAGE(C11,D11) -> 80748.625
B12: Agosto | C12: {=SUMPRODUCT((MONTH(Ventas!B3:B281)=8)*Ventas!K3:K281)} -> 198255 | D12: {=SUMPRODUCT((MONTH(Ventas!B3:B281)=8)*1)} -> 26 | E12: =AVERAGE(C12,D12) -> 99140.5
B13: Septiembre | C13: {=SUMPRODUCT((MONTH(Ventas!B3:B281)=9)*Ventas!K3:K281)} -> 92314.75 | D13: {=SUMPRODUCT((MONTH(Ventas!B3:B281)=9)*1)} -> 22 | E13: =AVERAGE(C13,D13) -> 46168.375
B14: Octubre | C14: {=SUMPRODUCT((MONTH(Ventas!B3:B281)=10)*Ventas!K3:K281)} -> 162757 | D14: {=SUMPRODUCT((MONTH(Ventas!B3:B281)=10)*1)} -> 19 | E14: =AVERAGE(C14,D14) -> 81388
B15: Noviembre | C15: {=SUMPRODUCT((MONTH(Ventas!B3:B281)=11)*Ventas!K3:K281)} -> 90676.5 | D15: {=SUMPRODUCT((MONTH(Ventas!B3:B281)=11)*1)} -> 19 | E15: =AVERAGE(C15,D15) -> 45347.75
B16: Diciembre | C16: {=SUMPRODUCT((MONTH(Ventas!B3:B281)=12)*Ventas!K3:K281)} -> 101846.75 | D16: {=SUMPRODUCT((MONTH(Ventas!B3:B281)=12)*1)} -> 21 | E16: =AVERAGE(C16,D16) -> 50933.875
B17: TOTAL: | C17: =SUM(C5:C16) -> 1793322 | D17: =SUM(D5:D16) -> 279 | E17: =SUM(E5:E16) -> 896800.5

Sheet Ranking
B2: RANKING DE VENDEDORES Y CATEGORÍAS
B4: VENDEDORES
B5: Vendedor: | C5: Ingreso Neto: | D5: Nro. Ventas: | E5: % Participación:
B6: Ana Torres | C6: =SUMIF(Ventas!C3:C281, B6, Ventas!K3:K281) -> 360906 | D6: =COUNTIF(Ventas!C3:C281, B6) -> 49 | E6: =C6/SUM(C6:C11) -> 0.20124997
B7: Carlos Ríos | C7: =SUMIF(Ventas!C3:C281, B7, Ventas!K3:K281) -> 304999.5 | D7: =COUNTIF(Ventas!C3:C281, B7) -> 44 | E7: =C7/SUM(C6:C11) -> 0.17007515
B8: Diego Mora | C8: =SUMIF(Ventas!C3:C281, B8, Ventas!K3:K281) -> 270691.75 | D8: =COUNTIF(Ventas!C3:C281, B8) -> 44 | E8: =C8/SUM(C6:C11) -> 0.15094431
B9: Lucía Vega | C9: =SUMIF(Ventas!C3:C281, B9, Ventas!K3:K281) -> 302819.5 | D9: =COUNTIF(Ventas!C3:C281, B9) -> 46 | E9: =C9/SUM(C6:C11) -> 0.16885952
B10: Miguel Paz | C10: =SUMIF(Ventas!C3:C281, B10, Ventas!K3:K281) -> 366852.25 | D10: =COUNTIF(Ventas!C3:C281, B10) -> 54 | E10: =C10/SUM(C6:C11) -> 0.20456574
B11: Sofía Luna | C11: =SUMIF(Ventas!C3:C281, B11, Ventas!K3:K281) -> 187053 | D11: =COUNTIF(Ventas!C3:C281, B11) -> 42 | E11: =C11/SUM(C6:C11) -> 0.10430531
B13: CATEGORÍAS
B14: Categorías: | C14: Ingreso Neto: | D14: Nro. Ventas: | E14: % Participación:
B15: Laptops | C15: =SUMIF(Ventas!E3:E281, B15, Ventas!K3:K281) -> 909400 | D15: =COUNTIF(Ventas!E3:E281, B15) -> 53 | E15: =C15/SUM(C15:C19) -> 0.50710358
B16: Monitores | C16: =SUMIF(Ventas!E3:E281, B16, Ventas!K3:K281) -> 397792.5 | D16: =COUNTIF(Ventas!E3:E281, B16) -> 58 | E16: =C16/SUM(C15:C19) -> 0.22181878
B17: Periféricos | C17: =SUMIF(Ventas!E3:E281, B17, Ventas!K3:K281) -> 67833.5 | D17: =COUNTIF(Ventas!E3:E281, B17) -> 54 | E17: =C17/SUM(C15:C19) -> 0.037825611
B18: Redes | C18: =SUMIF(Ventas!E3:E281, B18, Ventas!K3:K281) -> 82777.5 | D18: =COUNTIF(Ventas!E3:E281, B18) -> 56 | E18: =C18/SUM(C15:C19) -> 0.046158749
B19: Software | C19: =SUMIF(Ventas!E3:E281, B19, Ventas!K3:K281) -> 335518.5 | D19: =COUNTIF(Ventas!E3:E281, B19) -> 58 | E19: =C19/SUM(C15:C19) -> 0.18709328

Sheet Tabla Dinámica
A1: TABLA DINÁMICA
A3: Suma de Ingreso_Neto | B3: Etiquetas de columna
A4: Etiquetas de fila | B4: Ana Torres | C4: Carlos Ríos | D4: Diego Mora | E4: Lucía Vega | F4: Miguel Paz | G4: Sofía Luna | H4: Total general
A5: Laptops | B5: 100225 | C5: 9520 | D5: 104075 | E5: 128040 | F5: 97215 | G5: 33380 | H5: 472455
A6: Periféricos | B6: 8918 | C6: 6140 | D6: 2091.5 | E6: 3710 | F6: 5164 | G6: 4161 | H6: 30184.5
A7: Software | B7: 16480.5 | C7: 5233 | D7: 24768 | E7: 3885 | F7: 66032.5 | G7: 32004 | H7: 148403
A8: Total general | B8: 125623.5 | C8: 20893 | D8: 130934.5 | E8: 135635 | F8: 168411.5 | G8: 69545 | H8: 651042.5

Sheet Ventas
A1: TECHPERU S.A.C. — REGISTRO DE VENTAS 2024
A2: ID_Venta | B2: Fecha | C2: Vendedor | D2: Región | E2: Categoría | F2: Producto | G2: Cantidad | H2: Precio_Unit | I2: Descuento | J2: Ingreso_Bruto | K2: Ingreso_Neto | L2: Costo_Unit | M2: Ganancia | N2: Estado Meta
A3: V-0001 | B3: 2024-01-04 | C3: Diego Mora | D3: Lima Este | E3: Laptops | F3: HP Pavilion 15 | G3: 4 | H3: 2500 | I3: 0 | J3: =G3*H3 -> 10000 | K3: =J3*(1-I3) -> 10000 | L3: 1427.33 | M3: =K3-G3*L3 -> 4290.68 | N3: =IF(K3>=5000,"Meta Cumplida","Meta No Alcanzada") -> Meta Cumplida
A4: V-0002 | B4: 2024-01-08 | C4: Sofía Luna | D4: Lima Centro | E4: Redes | F4: Router TP-Link | G4: 1 | H4: 180 | I4: 0 | J4: =G4*H4 -> 180 | K4: =J4*(1-I4) -> 180 | L4: 101.53 | M4: =K4-G4*L4 -> 78.47 | N4: =IF(K4>=5000,"Meta Cumplida","Meta No Alcanzada") -> Meta No Alcanzada
A5: V-0003 | B5: 2024-01-14 | C5: Sofía Luna | D5: Lima Sur | E5: Redes | F5: Router TP-Link | G5: 12 | H5: 180 | I5: 0.15 | J5: =G5*H5 -> 2160 | K5: =J5*(1-I5) -> 1836 | L5: 117.94 | M5: =K5-G5*L5 -> 420.72 | N5: =IF(K5>=5000,"Meta Cumplida","Meta No Alcanzada") -> Meta No Alcanzada
A6: V-0004 | B6: 2024-01-06 | C6: Sofía Luna | D6: Lima Este | E6: Monitores | F6: BenQ 22" | G6: 13 | H6: 480 | I6: 0 | J6: =G6*H6 -> 6240 | K6: =J6*(1-I6) -> 6240 | L6: 318.63 | M6: =K6-G6*L6 -> 2097.81 | N6: =IF(K6>=5000,"Meta Cumplida","Meta No Alcanzada") -> Meta Cumplida
A7: V-0005 | B7: 2024-01-13 | C7: Lucía Vega | D7: Lima Sur | E7: Software | F7: AutoCAD 2024 | G7: 4 | H7: 1800 | I7: 0 | J7: =G7*H7 -> 7200 | K7: =J7*(1-I7) -> 7200 | L7: 1017.6 | M7: =K7-G7*L7 -> 3129.6 | N7: =IF(K7>=5000,"Meta Cumplida","Meta No Alcanzada") -> Meta Cumplida
A8: V-0006 | B8: 2024-01-18 | C8: Lucía Vega | D8: Callao | E8: Laptops | F8: Dell Inspiron | G8: 5 | H8: 2800 | I8: 0 | J8: =G8*H8 -> 14000 | K8: =J8*(1-I8) -> 14000 | L8: 1846.49 | M8: =K8-G8*L8 -> 4767.55 | N8: =IF(K8>=5000,"Meta Cumplida","Meta No Alcanzada") -> Meta Cumplida
A9: V-0007 | B9: 2024-01-28 | C9: Ana Torres | D9: Callao | E9: Laptops | F9: Asus VivoBook | G9: 5 | H9: 2100 | I9: 0.15 | J9: =G9*H9 -> 10500 | K9: =J9*(1-I9) -> 8925 | L9: 1349.83 | M9: =K9-G9*L9 -> 2175.85 | N9: =IF(K9>=5000,"Meta Cumplida","Meta No Alcanzada") -> Meta Cumplida
A10: V-0008 | B10: 2024-01-10 | C10: Diego Mora | D10: Lima Norte | E10: Periféricos | F10: Mouse Gamer | G10: 1 | H10: 85 | I10: 0.15 | J10: =G10*H10 -> 85 | K10: =J10*(1-I10) -> 72.25 | L10: 49.66 | M10: =K10-G10*L10 -> 22.59 | N10: =IF(K10>=5000,"Meta Cumplida","Meta No Alcanzada") -> Meta No Alcanzada
A11: V-0009 | B11: 2024-01-12 | C11: Ana Torres | D11: Lima Centro | E11: Laptops | F11: Lenovo IdeaPad | G11: 5 | H11: 2200 | I11: 0.05 | J11: =G11*H11 -> 11000 | K11: =J11*(1-I11) -> 10450 | L11: 1419.78 | M11: =K11-G11*L11 -> 3351.1 | N11: =IF(K11>=5000,"Meta Cumplida","Meta No Alcanzada") -> Meta Cumplida
A12: V-0010 | B12: 2024-01-22 | C12: Lucía Vega | D12: Lima Sur | E12: Monitores | F12: Dell UltraSharp | G12: 11 | H12: 1200 | I12: 0 | J12: =G12*H12 -> 13200 | K12: =J12*(1-I12) -> 13200 | L12: 786.33 | M12: =K12-G12*L12 -> 4550.37 | N12: =IF(K12>=5000,"Meta Cumplida","Meta No Alcanzada") -> Meta Cumplida
A13: V-0011 | B13: 2024-01-09 | C13: Sofía Luna | D13: Provincias | E13: Laptops | F13: Lenovo IdeaPad | G13: 4 | H13: 2200 | I13: 0 | J13: =G13*H13 -> 8800 | K13: =J13*(1-I13) -> 8800 | L13: 1362.55 | M13: =K13-G13*L13 -> 3349.8 | N13: =IF(K13>=5000,"Meta Cumplida","Meta No Alcanzada") -> Meta Cumplida
A14: V-0012 | B14: 2024-01-02 | C14: Diego Mora | D14: Lima Este | E14: Redes | F14: Switch 8 puertos | G14: 14 | H14: 220 | I14: 0 | J14: =G14*H14 -> 3080 | K14: =J14*(1-I14) -> 3080 | L14: 128.56 | M14: =K14-G14*L14 -> 1280.16 | N14: =IF(K14>=5000,"Meta Cumplida","Meta No Alcanzada") -> Meta No Alcanzada
... A281: V-0279 | B281: 2024-12-07 | C281: Ana Torres | D281: Lima Centro | E281: Software | F281: Office 365 Anual | G281: 9 | H281: 350 | I281: 0.05 | J281: =G281*H281 -> 3150 | K281: =J281*(1-I281) -> 2992.5 | L281: 243.25 | M281: =K281-G281*L281 -> 803.25 | N281: =IF(K281>=5000,"Meta Cumplida","Meta No Alcanzada") -> Meta No Alcanzada

Sheet Empleados
A1: TECHPERU S.A.C. — DIRECTORIO DE EMPLEADOS
A2: ID_Emp | B2: Nombre | C2: Apellido | D2: Departamento | E2: Cargo | F2: Región | G2: Fecha_Ingreso | H2: Salario_Base | I2: Bono_% | J2: Salario_Total
A3: E001 | B3: Ana | C3: Torres | D3: Ventas | E3: Ejecutiva Senior | F3: Lima Norte | G3: 2020-03-15 | H3: 4500 | I3: 0.15 | J3: =H3*(1+I3) -> 5175
A4: E002 | B4: Carlos | C4: Ríos | D4: Ventas | E4: Ejecutivo | F4: Lima Sur | G4: 2021-06-01 | H4: 3800 | I4: 0.12 | J4: =H4*(1+I4) -> 4256
A5: E003 | B5: Lucía | C5: Vega | D5: Ventas | E5: Ejecutiva Senior | F5: Lima Este | G5: 2019-11-20 | H5: 4800 | I5: 0.18 | J5: =H5*(1+I5) -> 5664
A6: E004 | B6: Miguel | C6: Paz | D6: Ventas | E6: Ejecutivo | F6: Lima Centro | G6: 2022-01-10 | H6: 3600 | I6: 0.1 | J6: =H6*(1+I6) -> 3960
A7: E005 | B7: Sofía | C7: Luna | D7: Ventas | E7: Ejecutiva | F7: Callao | G7: 2021-09-05 | H7: 3900 | I7: 0.12 | J7: =H7*(1+I7) -> 4368
A8: E006 | B8: Diego | C8: Mora | D8: Ventas | E8: Ejecutivo | F8: Provincias | G8: 2023-02-14 | H8: 3500 | I8: 0.08 | J8: =H8*(1+I8) -> 3780
A9: E007 | B9: Patricia | C9: Chávez | D9: RRHH | E9: Jefa de RRHH | F9: Lima Centro | G9: 2018-07-01 | H9: 5200 | I9: 0.2 | J9: =H9*(1+I9) -> 6240
A10: E008 | B10: Roberto | C10: Sánchez | D10: TI | E10: Analista TI | F10: Lima Centro | G10: 2020-05-15 | H10: 4200 | I10: 0.1 | J10: =H10*(1+I10) -> 4620
A11: E009 | B11: Valeria | C11: Flores | D11: Contabilidad | E11: Contadora Senior | F11: Lima Centro | G11: 2019-03-01 | H11: 4900 | I11: 0.15 | J11: =H11*(1+I11) -> 5635
A12: E010 | B12: Andrés | C12: Mendoza | D12: Marketing | E12: Jefe Marketing | F12: Lima Centro | G12: 2021-04-20 | H12: 5100 | I12: 0.18 | J12: =H12*(1+I12) -> 6018
A13: E011 | B13: Carmen | C13: Ruiz | D13: Logística | E13: Coordinadora | F13: Callao | G13: 2022-07-11 | H13: 3700 | I13: 0.1 | J13: =H13*(1+I13) -> 4070
A14: E012 | B14: Fernando | C14: Castillo | D14: Gerencia | E14: Gerente General | F14: Lima Centro | G14: 2017-01-02 | H14: 8500 | I14: 0.25 | J14: =H14*(1+I14) -> 10625
... A17: E015 | B17: Natalia | C17: Paredes | D17: Marketing | E17: Diseñadora | F17: Lima Norte | G17: 2022-03-28 | H17: 3800 | I17: 0.1 | J17: =H17*(1+I17) -> 4180
